dara/components/__init__.py
dara/components/_assets/__init__.py
dara/components/_assets/auto_js/.gitkeep
dara/components/_assets/auto_js/dara.components.css
dara/components/_assets/auto_js/dara.components.umd.js
dara/components/_assets/common/bokeh-3.1.1.min.js
dara/components/_assets/common/bokeh-api-3.1.1.min.js
dara/components/_assets/common/bokeh-gl-3.1.1.min.js
dara/components/_assets/common/bokeh-mathjax-3.1.1.min.js
dara/components/_assets/common/bokeh-tables-3.1.1.min.js
dara/components/_assets/common/bokeh-widgets-3.1.1.min.js
dara/components/_assets/common/pixi-filters.min.js
dara/components/_assets/common/pixi.min.js
dara/components/_assets/common/pixi_viewport.js
dara/components/_assets/common/plotly.min.js
dara/components/common/__init__.py
dara/components/common/accordion.py
dara/components/common/anchor.py
dara/components/common/base_component.py
dara/components/common/bullet_list.py
dara/components/common/button.py
dara/components/common/button_bar.py
dara/components/common/card.py
dara/components/common/carousel.py
dara/components/common/checkbox_group.py
dara/components/common/code.py
dara/components/common/component_select_list.py
dara/components/common/datepicker.py
dara/components/common/dropdown_menu.py
dara/components/common/dropzone.py
dara/components/common/form.py
dara/components/common/form_page.py
dara/components/common/grid.py
dara/components/common/heading.py
dara/components/common/html_raw.py
dara/components/common/icon.py
dara/components/common/if_cmp.py
dara/components/common/image.py
dara/components/common/input.py
dara/components/common/label.py
dara/components/common/markdown.py
dara/components/common/modal.py
dara/components/common/overlay.py
dara/components/common/paragraph.py
dara/components/common/progress_bar.py
dara/components/common/radio_group.py
dara/components/common/select.py
dara/components/common/slider.py
dara/components/common/spacer.py
dara/components/common/stack.py
dara/components/common/switch.py
dara_components-1.25.1.dist-info/LICENSE
dara_components-1.25.1.dist-info/METADATA
dara_components-1.25.1.dist-info/WHEEL
dara_components-1.25.1.dist-info/entry_points.txt
dara_components-1.25.1.dist-info/RECORD
