Metadata-Version: 2.1
Name: dara-components
Version: 1.25.1
Summary: Components for the Dara Framework
Home-page: https://dara.causalens.com/
License: Apache-2.0
Author: Patricia Jacob
Author-email: patricia@causalens.com
Requires-Python: >=3.10.0,<3.13.0
Classifier: License :: OSI Approved :: Apache Software License
Classifier: Programming Language :: Python :: 3
Classifier: Programming Language :: Python :: 3.10
Classifier: Programming Language :: Python :: 3.11
Classifier: Programming Language :: Python :: 3.12
Requires-Dist: bokeh (==3.1.1)
Requires-Dist: cai-causal-graph (>=0.3.6)
Requires-Dist: certifi (>=2024.7.4)
Requires-Dist: dara-core (==1.25.1)
Requires-Dist: dill (>=0.3.0,<0.4.0)
Requires-Dist: matplotlib (>=2.0.0)
Requires-Dist: pandas (>=1.1.0,<3.0.0)
Requires-Dist: plotly (>=5.14.0,<5.15.0)
Requires-Dist: scipy
Requires-Dist: seaborn (>=0.11.0)
Project-URL: Repository, https://github.com/causalens/dara
